moondb/__init__.py
moondb/core.py
moondb/helpers.py
pymoondb-0.1.dist-info/LICENSE
pymoondb-0.1.dist-info/METADATA
pymoondb-0.1.dist-info/WHEEL
pymoondb-0.1.dist-info/top_level.txt
pymoondb-0.1.dist-info/RECORD
