Metadata-Version: 2.1
Name: pymoondb
Version: 0.1
Summary: Accessing the MoonDB lunar sample database
Home-page: https://www.ict.inaf.it/gitlab/alessandro.frigeri/pymoondb
Author: Alessandro Frigeri
Author-email: Alessandro.Frigeri@inaf.it
License: MIT
Platform: UNKNOWN
Requires-Dist: markdown
Requires-Dist: requests
Requires-Dist: urllib3
